d2ipy/__init__.py
d2ipy/glavni.py
d2ipy/mymodule/__init__.py
d2ipy/mymodule/myfunctions.py
d2ipy-0.0.1.dist-info/METADATA
d2ipy-0.0.1.dist-info/RECORD
d2ipy-0.0.1.dist-info/WHEEL
d2ipy-0.0.1.dist-info/top_level.txt
