Metadata-Version: 2.1
Name: d2ipy
Version: 0.0.1
Summary: Pacquets python pour le service D2i
Home-page: UNKNOWN
Author: Example Author
Author-email: marrkonni@yahoo.com
License: UNKNOWN
Platform: UNKNOWN
Classifier: Programming Language :: Python :: 3
Classifier: License :: OSI Approved :: MIT License
Classifier: Operating System :: OS Independent
